hu_graphql_client/__init__.py
hu_graphql_client/all_users.py
hu_graphql_client/async_base_client.py
hu_graphql_client/base_model.py
hu_graphql_client/business.py
hu_graphql_client/businesses.py
hu_graphql_client/case_studies.py
hu_graphql_client/case_study.py
hu_graphql_client/client.py
hu_graphql_client/compound.py
hu_graphql_client/compounds.py
hu_graphql_client/create_business_with_relations.py
hu_graphql_client/create_case_study.py
hu_graphql_client/create_compound.py
hu_graphql_client/create_episode.py
hu_graphql_client/create_person.py
hu_graphql_client/create_product.py
hu_graphql_client/create_protocol.py
hu_graphql_client/create_user_protocol.py
hu_graphql_client/delete_all_episodes.py
hu_graphql_client/delete_business.py
hu_graphql_client/delete_compound.py
hu_graphql_client/delete_episode.py
hu_graphql_client/delete_person.py
hu_graphql_client/delete_product.py
hu_graphql_client/delete_protocol.py
hu_graphql_client/delete_user.py
hu_graphql_client/delete_user_profile.py
hu_graphql_client/delete_user_protocol.py
hu_graphql_client/embed_business_description.py
hu_graphql_client/embed_person_bio.py
hu_graphql_client/embed_product_description.py
hu_graphql_client/enums.py
hu_graphql_client/episode.py
hu_graphql_client/episodes.py
hu_graphql_client/exceptions.py
hu_graphql_client/input_types.py
hu_graphql_client/login.py
hu_graphql_client/me.py
hu_graphql_client/my_profile.py
hu_graphql_client/my_user_protocols.py
hu_graphql_client/people.py
hu_graphql_client/person.py
hu_graphql_client/product.py
hu_graphql_client/products.py
hu_graphql_client/protocol.py
hu_graphql_client/protocols.py
hu_graphql_client/register.py
hu_graphql_client/save_entity.py
hu_graphql_client/saved_entities.py
hu_graphql_client/unsave_entity.py
hu_graphql_client/update_business.py
hu_graphql_client/update_business_relations.py
hu_graphql_client/update_case_study.py
hu_graphql_client/update_compound.py
hu_graphql_client/update_compound_relations.py
hu_graphql_client/update_episode.py
human_upgrade_graphql_client-0.1.19.dist-info/METADATA
human_upgrade_graphql_client-0.1.19.dist-info/WHEEL
human_upgrade_graphql_client-0.1.19.dist-info/RECORD
