Metadata-Version: 2.4
Name: human-upgrade-graphql-client
Version: 0.1.19
Summary: Python GraphQL client for Human Upgrade schema
Requires-Python: >=3.11
Requires-Dist: httpx>=0.27
Requires-Dist: pydantic>=2.0
Provides-Extra: dev
Requires-Dist: ariadne-codegen; extra == 'dev'
Requires-Dist: build; extra == 'dev'
